bindos/__init__.py
bindos/cli.py
bindos/core.py
bindos/pro_engine.py
bindos-0.2.0.dist-info/METADATA
bindos-0.2.0.dist-info/WHEEL
bindos-0.2.0.dist-info/entry_points.txt
bindos-0.2.0.dist-info/top_level.txt
bindos-0.2.0.dist-info/RECORD
