Metadata-Version: 2.4
Name: bindos
Version: 0.2.0
Summary: Curvature-based time-series stabilizer with ZOL-Q two-branch Pro engine
Author: Chad Obie
License-Expression: MIT
Project-URL: Homepage, https://github.com/TheOneTheOnlyTheChad/bindos
Requires-Python: >=3.10
Requires-Dist: numpy
Requires-Dist: matplotlib
